LICENSE
MANIFEST.in
README.md
pyproject.toml
setup.cfg
setup.py
rio_tiler_mvt/__init__.py
rio_tiler_mvt/mvt.c
rio_tiler_mvt/mvt.pyx
rio_tiler_mvt.egg-info/PKG-INFO
rio_tiler_mvt.egg-info/SOURCES.txt
rio_tiler_mvt.egg-info/dependency_links.txt
rio_tiler_mvt.egg-info/not-zip-safe
rio_tiler_mvt.egg-info/requires.txt
rio_tiler_mvt.egg-info/top_level.txt
tests/test_mvt.py