Metadata-Version: 2.2
Name: rio-tiler-mvt
Version: 0.2.0
Summary: A rio-tiler plugin to encode tile array to MVT
Home-page: https://github.com/cogeotiff/rio-tiler-mvt
Author: Vincent Sarago
Author-email: vincent@developmentseed.org
License: MIT
Keywords: COG MVT mapbox vectortile GIS
Classifier: Intended Audience :: Information Technology
Classifier: Intended Audience :: Science/Research
Classifier: License :: OSI Approved :: MIT License
Classifier: Programming Language :: Python :: 3.9
Classifier: Programming Language :: Python :: 3.10
Classifier: Programming Language :: Python :: 3.11
Classifier: Programming Language :: Python :: 3.12
Classifier: Programming Language :: Python :: 3.13
Classifier: Topic :: Scientific/Engineering :: GIS
Requires-Python: >=3.9
License-File: LICENSE
Requires-Dist: numpy
Requires-Dist: vtzero
Requires-Dist: rasterio
Requires-Dist: shapely
Provides-Extra: test
Requires-Dist: protobuf==3.20.1; extra == "test"
Requires-Dist: rio-tiler>=2.0; extra == "test"
Requires-Dist: pytest; extra == "test"
Requires-Dist: pytest-cov; extra == "test"
Provides-Extra: dev
Requires-Dist: pre-commit; extra == "dev"
Dynamic: author
Dynamic: author-email
Dynamic: classifier
Dynamic: description
Dynamic: description-content-type
Dynamic: home-page
Dynamic: keywords
Dynamic: license
Dynamic: provides-extra
Dynamic: requires-dist
Dynamic: requires-python
Dynamic: summary
